{
  "kanban": [
    {
      "id": "1",
      "name": "To Do",
      "cards": [
        {
          "id": 1,
          "title": "Fazer convite padrinhos",
          "date_created": "2024-02-22 08:00",
          "date_end": null,
          "badges": [
            {
              "id": 1,
              "name": "Novo",
              "cor": "#A9DEF9"
            },
            {
              "id": 5,
              "name": "Médio",
              "cor": "#FCF6BD"
            }
          ],
          "description": ""
        },
        {
          "id": 6,
          "title": "Feito",
          "date_created": "2024-02-29T19:30:49.058Z",
          "date_end": null,
          "badges": [],
          "description": null
        }
      ]
    },
    {
      "id": "2",
      "name": "In Progress",
      "cards": [
        {
          "id": 2,
          "title": "Contratar porta",
          "date_created": "2024-02-22 08:00",
          "date_end": "2024-02-29 08:00",
          "badges": [
            {
              "id": 1,
              "name": "Novo",
              "cor": "#A9DEF9"
            },
            {
              "id": 6,
              "name": "Dificil",
              "cor": "#FAC8D6"
            }
          ],
          "description": "Lorem ipsum dolor sit amet, consectetur adipiscing elit.Duis aliquam ipsum sit amet erat ullamcorper venenatis sed eu arcu.Etiam pharetra magna eget tortor laoreet, eu imperdiet nisl tincidunt.Ut nec ipsum orci."
        },
        {
          "id": 3,
          "title": "Teste",
          "date_created": "2024-02-29T19:30:27.028Z",
          "date_end": null,
          "badges": [],
          "description": null
        }
      ]
    },
    {
      "id": "3",
      "name": "Done",
      "cards": [
        {
          "id": 4,
          "title": "Done",
          "date_created": "2024-02-29T19:30:36.948Z",
          "date_end": null,
          "badges": [],
          "description": null
        },
        {
          "id": 5,
          "title": "Agora",
          "date_created": "2024-02-29T19:30:43.146Z",
          "date_end": null,
          "badges": [],
          "description": null
        }
      ]
    }
  ],
  "badges": [
    {
      "id": "1",
      "name": "Novo",
      "cor": "#A9DEF9"
    },
    {
      "id": "2",
      "name": "Defeito",
      "cor": "#FF99C8"
    },
    {
      "id": "3",
      "name": "Documentação",
      "cor": "#E4C1F9"
    },
    {
      "id": "4",
      "name": "Facil",
      "cor": "#D0F4DE"
    },
    {
      "id": "5",
      "name": "Médio",
      "cor": "#FCF6BD"
    },
    {
      "id": "6",
      "name": "Dificil",
      "cor": "#FAC8D6"
    }
  ]
}